cpplint_fix/__init__.py
cpplint_fix/__main__.py
cpplint_fix/config.py
cpplint_fix/parser.py
cpplint_fix/source.py
cpplint_fix/wrapper.py
cpplint_fix/edits/__init__.py
cpplint_fix/edits/__main__.py
cpplint_fix/edits/base.py
cpplint_fix/edits/whitespace.py
cpplint_fix-0.1.0.dist-info/METADATA
cpplint_fix-0.1.0.dist-info/WHEEL
cpplint_fix-0.1.0.dist-info/entry_points.txt
cpplint_fix-0.1.0.dist-info/licenses/LICENSE
cpplint_fix-0.1.0.dist-info/RECORD
