Metadata-Version: 2.4
Name: cpplint-fix
Version: 0.1.0
Summary: Add your description here
License-File: LICENSE
Requires-Python: >=3.9
Requires-Dist: cpplint>=2.0.2
Requires-Dist: pydantic>=2.11.7
Requires-Dist: pyyaml>=6.0.2
